check_pa/__init__.py
check_pa/check_paloalto.py
check_pa/utils.py
check_pa/xml_reader.py
check_pa/modules/__init__.py
check_pa/modules/certificate.py
check_pa/modules/diskspace.py
check_pa/modules/environmental.py
check_pa/modules/load.py
check_pa/modules/sessioninfo.py
check_pa/modules/thermal.py
check_pa/modules/throughput.py
check_pa/modules/useragent.py
check_paloalto-0.3.2.dist-info/DESCRIPTION.rst
check_paloalto-0.3.2.dist-info/METADATA
check_paloalto-0.3.2.dist-info/RECORD
check_paloalto-0.3.2.dist-info/WHEEL
check_paloalto-0.3.2.dist-info/entry_points.txt
check_paloalto-0.3.2.dist-info/metadata.json
check_paloalto-0.3.2.dist-info/top_level.txt
