Metadata-Version: 2.0
Name: check-paloalto
Version: 0.3.2
Summary: check_paloalto is a Nagios/Icinga plugin for Palo Alto Next Generation Firewalls. It is written in Python and based on the PA REST API.
Home-page: https://github.com/ralph-hm/nagios_check_paloalto
Author: Ralph Offinger
Author-email: ralph.offinger@gmail.com
License: CC BY-ND 4.0
Keywords: paloalto icinga nagios check
Platform: UNKNOWN
Classifier: Development Status :: 4 - Beta
Classifier: Intended Audience :: Developers
Classifier: Intended Audience :: System Administrators
Classifier: Topic :: System :: Monitoring
Classifier: License :: OSI Approved :: Common Public License
Classifier: Programming Language :: Python :: 2
Classifier: Programming Language :: Python :: 2.7
Classifier: Programming Language :: Python :: 3
Classifier: Programming Language :: Python :: 3.3
Classifier: Programming Language :: Python :: 3.4
Classifier: Programming Language :: Python :: 3.5
Requires-Dist: beautifulsoup4
Requires-Dist: lxml
Requires-Dist: nagiosplugin
Requires-Dist: requests
